harichselvamc/__init__.py
harichselvamc/triangle.py
harichselvamc/wifipassword.py
harichselvamc-0.7.2.dist-info/METADATA
harichselvamc-0.7.2.dist-info/WHEEL
harichselvamc-0.7.2.dist-info/top_level.txt
harichselvamc-0.7.2.dist-info/RECORD
