Metadata-Version: 2.2
Name: harichselvamc
Version: 0.7.2
Summary: A Python package to generate Pascal's Triangle and retrieve Wi-Fi passwords.
Home-page: https://github.com/harichselvamc/harichselvamc-package
Author: harichselvam
Author-email: harichselvamc@gmail.com
Classifier: Programming Language :: Python :: 3
Classifier: License :: OSI Approved :: MIT License
Classifier: Operating System :: OS Independent
Dynamic: author
Dynamic: author-email
Dynamic: classifier
Dynamic: description
Dynamic: description-content-type
Dynamic: home-page
Dynamic: summary
